{
 "meta": {
  "sourceHash": "3d660fff812cc94642fe9384efba1eab9d0e05bfceec8e970af81b21a26840b3",
  "engine": "opus-4-8",
  "translatedAt": "2026-07-10",
  "sourceLang": "en"
 },
 "fields": {
  "keyRules": [
   "Maksimalt 120 m over jorden (EASA Åben kategori)",
   "Registrer dig som UAS-operatør (gratis), hvis dronen vejer 250 g eller mere eller har et kamera",
   "A1/A3-onlinekursus er påkrævet — minimumsalder 16 år",
   "Beskyttede arkæologiske steder: Akropolis, Delfi, Olympia og andre",
   "Hold altid dronen inden for synsvidde (VLOS)",
   "Flyv aldrig over mennesker, folkemængder eller offentlige arrangementer",
   "En minimumsafstand på 8 km fra hver lufthavn",
   "Natflyvning er forbudt uden særlig tilladelse",
   "Ø-lufthavne: Tjek DAGR-kortet omhyggeligt — mange øer har store CTR'er"
  ],
  "importantNotes": [
   "Arkæologiske steder og kulturarvsmindesmærker er strengt forbudte — der gælder store bøder",
   "Ø-lufthavne skaber omfattende restriktionszoner",
   "Militæranlæg: absolutte flyveforbudszoner (mange på øer)",
   "GDPR gælder, når der optages identificerbare personer"
  ],
  "primaryLinks": [
   {
    "title": "HCAA — Regler om droner",
    "description": "Officielle regler og information om droner fra luftfartsvæsenet"
   },
   {
    "title": "HCAA — Pilotregistrering",
    "description": "Gratis registrering som UAS-operatør (gyldig i alle EU/EASA-lande)"
   },
   {
    "title": "DAGR — Luftrumskort for droner",
    "description": "Officielt geografisk kort over restriktioner for droneflyvning i Grækenland"
   },
   {
    "title": "HCAA — Flyveanmeldelse",
    "description": "Indsendelse af en flyveanmeldelse 5 dage i forvejen (påkrævet for hver flyvning)"
   }
  ],
  "secondaryLinks": [
   {
    "title": "HASP — Luftsport",
    "description": "Det græske luftsportsforbund og information om rekreativ flyvning"
   },
   {
    "title": "HCAA — Ofte stillede spørgsmål om droner",
    "description": "Ofte stillede spørgsmål om droneregler i Grækenland"
   }
  ],
  "disclaimerText": "Tjek altid de officielle kilder fra det græske luftfartsvæsen (HCAA) og DAGR-kortet før hver flyvning. Denne app er et værktøj — ikke en juridisk myndighed. Grækenland følger EASA-reglerne med nationale tilføjelser, herunder blandt andet det obligatoriske krav om flyveanmeldelse 5 dage i forvejen.",
  "sectionLabelRules": "GRUNDLÆGGENDE REGLER (EASA ÅBEN KLASSE)",
  "sectionLabelPrimary": "OFFICIELLE KILDER",
  "sectionLabelSecondary": "YDERLIGERE RESSOURCER",
  "linksSheetTitle": "Luftrum og regler — Grækenland",
  "dronePilotCredentialName": "Operatørcertifikat"
 }
}
